{
  "$schema": "https://static.modelcontextprotocol.io/schemas/2025-12-11/server.schema.json",
  "name": "io.github.junhui20/mycal",
  "description": "Malaysia public holidays, school terms, business days & a leave optimizer (13 tools).",
  "repository": {
    "url": "https://github.com/Junhui20/malaysia-calendar-api",
    "source": "github"
  },
  "version": "0.1.3",
  "packages": [
    {
      "registryType": "npm",
      "identifier": "@catlabtech/mycal-mcp-server",
      "version": "0.1.3",
      "transport": { "type": "stdio" }
    }
  ]
}
